<?xml version="1.0" encoding="utf-8" ?><dwsync><file name="de.js" server="https://cams.unt.edu:8443/" local="3416597158" remote="16301826997" /><file name="dk.js" server="https://cams.unt.edu:8443/" local="3416597159" remote="16301826998" /><file name="en.js" server="https://cams.unt.edu:8443/" local="3416597159" remote="16301827000" /><file name="fr.js" server="https://cams.unt.edu:8443/" local="3416597159" remote="16301827001" /><file name="hr.js" server="https://cams.unt.edu:8443/" local="3416597159" remote="16301827002" /><file name="it.js" server="https://cams.unt.edu:8443/" local="3416597160" remote="16301827004" /><file name="ja.js" server="https://cams.unt.edu:8443/" local="3416597157" remote="16301827005" /><file name="nl.js" server="https://cams.unt.edu:8443/" local="3416597158" remote="16301827006" /><file name="pl.js" server="https://cams.unt.edu:8443/" local="3416597160" remote="16301827007" /><file name="pt.js" server="https://cams.unt.edu:8443/" local="3416597158" remote="16301827008" /><file name="zh_cn.js" server="https://cams.unt.edu:8443/" local="3416597157" remote="16301827010" /></dwsync>